ffpb.py
ffpb-0.4.1.dist-info/COPYING
ffpb-0.4.1.dist-info/METADATA
ffpb-0.4.1.dist-info/WHEEL
ffpb-0.4.1.dist-info/entry_points.txt
ffpb-0.4.1.dist-info/top_level.txt
ffpb-0.4.1.dist-info/zip-safe
ffpb-0.4.1.dist-info/RECORD
