Metadata-Version: 2.1
Name: ffpb
Version: 0.4.1
Summary: A progress bar for ffmpeg. Yay !
Home-page: https://github.com/althonos/ffpb
Author: Martin Larralde
Author-email: martin.larralde@ens-paris-saclay.fr
License: MIT
Project-URL: Bug Tracker, https://github.com/althonos/ffpb/issues
Project-URL: Changelog, https://github.com/althonos/ffpb/blob/master/CHANGELOG.md
Keywords: ffmpeg,ffmpeg-command,progress-bar,python-script,cli
Platform: any
Classifier: Development Status :: 4 - Beta
Classifier: Environment :: Console
Classifier: License :: OSI Approved :: MIT License
Classifier: Operating System :: Unix
Classifier: Programming Language :: Python
Classifier: Programming Language :: Python :: 2.7
Classifier: Programming Language :: Python :: 3.3
Classifier: Programming Language :: Python :: 3.4
Classifier: Programming Language :: Python :: 3.5
Classifier: Programming Language :: Python :: 3.6
Classifier: Programming Language :: Python :: 3.7
Classifier: Programming Language :: Python :: 3.8
Classifier: Topic :: Multimedia :: Video :: Conversion
Requires-Python: !=3.0.*,!=3.1.*,!=3.2.*,>=2.7
Requires-Dist: tqdm (~=4.25)
